{
    "keep": {
        "days": false,
        "amount": 31
    },
    "auditLog": "logs/.audit/app-error.json",
    "files": [
        {
            "date": 1738947102113,
            "name": "logs/app-error.2025-02-08.log",
            "hash": "122bf669ee16dd437ac8f8ae84df2f2910180ec67f861b26646813973c203c0f"
        },
        {
            "date": 1739107867501,
            "name": "logs/app-error.2025-02-09.log",
            "hash": "9311d7f8e67bd4f6343d180fcca0bc84a3a67d200598edb3c330890713594a7b"
        },
        {
            "date": 1739585953820,
            "name": "logs/app-error.2025-02-15.log",
            "hash": "064efd2bdf7a365384761750be2c29a4d11482c7c8e4d9736bb83fd70124694d"
        },
        {
            "date": 1739805190925,
            "name": "logs/app-error.2025-02-17.log",
            "hash": "d664c8e2b41b9edf6c55eb3a0cedc1ada068ee122337045ede4a63790db50a6b"
        },
        {
            "date": 1739884469914,
            "name": "logs/app-error.2025-02-18.log",
            "hash": "2949debd0992a3f357659ff4ca08a7c86dee6be4fe7430531d6f3d2760ef9681"
        },
        {
            "date": 1739977784784,
            "name": "logs/app-error.2025-02-19.log",
            "hash": "1b0eaa577c7c21ff81e99ef4f1ddbd08859128e148993c71838b1d61d825762f"
        }
    ],
    "hashType": "sha256"
}